[{"mCalorie":0.0,"mDistance":0.0,"mNowHealthyStep":0,"mRunStepCount":0,"mSpeed":0.0,"mStartTime":0,"mStepCount":0,"mTimeUnit":600000,"mTotalActiveTime":0.0,"mWalkStepCount":0},{"mCalorie":0.3799999952316284,"mDistance":9.420000076293945,"mNowHealthyStep":0,"mRunStepCount":0,"mSpeed":5.700000286102295,"mStartTime":0,"mStepCount":12,"mTimeUnit":600000,"mTotalActiveTime":5949.473433771965,"mWalkStepCount":12},{"mCalorie":0.0,"mDistance":0.0,"mNowHealthyStep":0,"mRunStepCount":0,"mSpeed":0.0,"mStartTime":0,"mStepCount":0,"mTimeUnit":600000,"mTotalActiveTime":0.0,"mWalkStepCount":0},{"mCalorie":0.0,"mDistance":0.0,"mNowHealthyStep":0,"mRunStepCount":0,"mSpeed":0.0,"mStartTime":0,"mStepCount":0,"mTimeUnit":600000,"mTotalActiveTime":0.0,"mWalkStepCount":0},{"mCalorie":0.0,"mDistance":0.0,"mNowHealthyStep":0,"mRunStepCount":0,"mSpeed":0.0,"mStartTime":0,"mStepCount":0,"mTimeUnit":600000,"mTotalActiveTime":0.0,"mWalkStepCount":0},{"mCalorie":0.0,"mDistance":0.0,"mNowHealthyStep":0,"mRunStepCount":0,"mSpeed":0.0,"mStartTime":0,"mStepCount":0,"mTimeUnit":600000,"mTotalActiveTime":0.0,"mWalkStepCount":0},{"mCalorie":0.0,"mDistance":0.0,"mNowHealthyStep":0,"mRunStepCount":0,"mSpeed":0.0,"mStartTime":0,"mStepCount":0,"mTimeUnit":600000,"mTotalActiveTime":0.0,"mWalkStepCount":0},{"mCalorie":0.0,"mDistance":0.0,"mNowHealthyStep":0,"mRunStepCount":0,"mSpeed":0.0,"mStartTime":0,"mStepCount":0,"mTimeUnit":600000,"mTotalActiveTime":0.0,"mWalkStepCount":0},{"mCalorie":0.0,"mDistance":0.0,"mNowHealthyStep":0,"mRunStepCount":0,"mSpeed":0.0,"mStartTime":0,"mStepCount":0,"mTimeUnit":600000,"mTotalActiveTime":0.0,"mWalkStepCount":0},{"mCalorie":0.0,"mDistance":0.0,"mNowHealthyStep":0,"mRunStepCount":0,"mSpeed":0.0,"mStartTime":0,"mStepCount":0,"mTimeUnit":600000,"mTotalActiveTime":0.0,"mWalkStepCount":0},{"mCalorie":0.0,"mDistance":0.0,"mNowHealthyStep":0,"mRunStepCount":0,"mSpeed":0.0,"mStartTime":0,"mStepCount":0,"mTimeUnit":600000,"mTotalActiveTime":0.0,"mWalkStepCount":0},{"mCalorie":0.0,"mDistance":0.0,"mNowHealthyStep":0,"mRunStepCount":0,"mSpeed":0.0,"mStartTime":0,"mStepCount":0,"mTimeUnit":600000,"mTotalActiveTime":0.0,"mWalkStepCount":0},{"mCalorie":0.0,"mDistance":0.0,"mNowHealthyStep":0,"mRunStepCount":0,"mSpeed":0.0,"mStartTime":0,"mStepCount":0,"mTimeUnit":600000,"mTotalActiveTime":0.0,"mWalkStepCount":0},{"mCalorie":0.0,"mDistance":0.0,"mNowHealthyStep":0,"mRunStepCount":0,"mSpeed":0.0,"mStartTime":0,"mStepCount":0,"mTimeUnit":600000,"mTotalActiveTime":0.0,"mWalkStepCount":0},{"mCalorie":0.0,"mDistance":0.0,"mNowHealthyStep":0,"mRunStepCount":0,"mSpeed":0.0,"mStartTime":0,"mStepCount":0,"mTimeUnit":600000,"mTotalActiveTime":0.0,"mWalkStepCount":0},{"mCalorie":0.0,"mDistance":0.0,"mNowHealthyStep":0,"mRunStepCount":0,"mSpeed":0.0,"mStartTime":0,"mStepCount":0,"mTimeUnit":600000,"mTotalActiveTime":0.0,"mWalkStepCount":0},{"mCalorie":0.0,"mDistance":0.0,"mNowHealthyStep":0,"mRunStepCount":0,"mSpeed":0.0,"mStartTime":0,"mStepCount":0,"mTimeUnit":600000,"mTotalActiveTime":0.0,"mWalkStepCount":0},{"mCalorie":0.0,"mDistance":0.0,"mNowHealthyStep":0,"mRunStepCount":0,"mSpeed":0.0,"mStartTime":0,"mStepCount":0,"mTimeUnit":600000,"mTotalActiveTime":0.0,"mWalkStepCount":0},{"mCalorie":0.0,"mDistance":0.0,"mNowHealthyStep":0,"mRunStepCount":0,"mSpeed":0.0,"mStartTime":0,"mStepCount":0,"mTimeUnit":600000,"mTotalActiveTime":0.0,"mWalkStepCount":0},{"mCalorie":0.0,"mDistance":0.0,"mNowHealthyStep":0,"mRunStepCount":0,"mSpeed":0.0,"mStartTime":0,"mStepCount":0,"mTimeUnit":600000,"mTotalActiveTime":0.0,"mWalkStepCount":0},{"mCalorie":0.0,"mDistance":0.0,"mNowHealthyStep":0,"mRunStepCount":0,"mSpeed":0.0,"mStartTime":0,"mStepCount":0,"mTimeUnit":600000,"mTotalActiveTime":0.0,"mWalkStepCount":0},{"mCalorie":0.0,"mDistance":0.0,"mNowHealthyStep":0,"mRunStepCount":0,"mSpeed":0.0,"mStartTime":0,"mStepCount":0,"mTimeUnit":600000,"mTotalActiveTime":0.0,"mWalkStepCount":0},{"mCalorie":0.0,"mDistance":0.0,"mNowHealthyStep":0,"mRunStepCount":0,"mSpeed":0.0,"mStartTime":0,"mStepCount":0,"mTimeUnit":600000,"mTotalActiveTime":0.0,"mWalkStepCount":0},{"mCalorie":0.0,"mDistance":0.0,"mNowHealthyStep":0,"mRunStepCount":0,"mSpeed":0.0,"mStartTime":0,"mStepCount":0,"mTimeUnit":600000,"mTotalActiveTime":0.0,"mWalkStepCount":0},{"mCalorie":0.0,"mDistance":0.0,"mNowHealthyStep":0,"mRunStepCount":0,"mSpeed":0.0,"mStartTime":0,"mStepCount":0,"mTimeUnit":600000,"mTotalActiveTime":0.0,"mWalkStepCount":0},{"mCalorie":0.0,"mDistance":0.0,"mNowHealthyStep":0,"mRunStepCount":0,"mSpeed":0.0,"mStartTime":0,"mStepCount":0,"mTimeUnit":600000,"mTotalActiveTime":0.0,"mWalkStepCount":0},{"mCalorie":0.0,"mDistance":0.0,"mNowHealthyStep":0,"mRunStepCount":0,"mSpeed":0.0,"mStartTime":0,"mStepCount":0,"mTimeUnit":600000,"mTotalActiveTime":0.0,"mWalkStepCount":0},{"mCalorie":0.0,"mDistance":0.0,"mNowHealthyStep":0,"mRunStepCount":0,"mSpeed":0.0,"mStartTime":0,"mStepCount":0,"mTimeUnit":600000,"mTotalActiveTime":0.0,"mWalkStepCount":0},{"mCalorie":0.0,"mDistance":0.0,"mNowHealthyStep":0,"mRunStepCount":0,"mSpeed":0.0,"mStartTime":0,"mStepCount":0,"mTimeUnit":600000,"mTotalActiveTime":0.0,"mWalkStepCount":0},{"mCalorie":0.0,"mDistance":0.0,"mNowHealthyStep":0,"mRunStepCount":0,"mSpeed":0.0,"mStartTime":0,"mStepCount":0,"mTimeUnit":600000,"mTotalActiveTime":0.0,"mWalkStepCount":0},{"mCalorie":0.0,"mDistance":0.0,"mNowHealthyStep":0,"mRunStepCount":0,"mSpeed":0.0,"mStartTime":0,"mStepCount":0,"mTimeUnit":600000,"mTotalActiveTime":0.0,"mWalkStepCount":0},{"mCalorie":0.0,"mDistance":0.0,"mNowHealthyStep":0,"mRunStepCount":0,"mSpeed":0.0,"mStartTime":0,"mStepCount":0,"mTimeUnit":600000,"mTotalActiveTime":0.0,"mWalkStepCount":0},{"mCalorie":0.0,"mDistance":0.0,"mNowHealthyStep":0,"mRunStepCount":0,"mSpeed":0.0,"mStartTime":0,"mStepCount":0,"mTimeUnit":600000,"mTotalActiveTime":0.0,"mWalkStepCount":0},{"mCalorie":0.0,"mDistance":0.0,"mNowHealthyStep":0,"mRunStepCount":0,"mSpeed":0.0,"mStartTime":0,"mStepCount":0,"mTimeUnit":600000,"mTotalActiveTime":0.0,"mWalkStepCount":0},{"mCalorie":0.0,"mDistance":0.0,"mNowHealthyStep":0,"mRunStepCount":0,"mSpeed":0.0,"mStartTime":0,"mStepCount":0,"mTimeUnit":600000,"mTotalActiveTime":0.0,"mWalkStepCount":0},{"mCalorie":0.0,"mDistance":0.0,"mNowHealthyStep":0,"mRunStepCount":0,"mSpeed":0.0,"mStartTime":0,"mStepCount":0,"mTimeUnit":600000,"mTotalActiveTime":0.0,"mWalkStepCount":0},{"mCalorie":0.0,"mDistance":0.0,"mNowHealthyStep":0,"mRunStepCount":0,"mSpeed":0.0,"mStartTime":0,"mStepCount":0,"mTimeUnit":600000,"mTotalActiveTime":0.0,"mWalkStepCount":0},{"mCalorie":0.0,"mDistance":0.0,"mNowHealthyStep":0,"mRunStepCount":0,"mSpeed":0.0,"mStartTime":0,"mStepCount":0,"mTimeUnit":600000,"mTotalActiveTime":0.0,"mWalkStepCount":0},{"mCalorie":0.0,"mDistance":0.0,"mNowHealthyStep":0,"mRunStepCount":0,"mSpeed":0.0,"mStartTime":0,"mStepCount":0,"mTimeUnit":600000,"mTotalActiveTime":0.0,"mWalkStepCount":0},{"mCalorie":0.0,"mDistance":0.0,"mNowHealthyStep":0,"mRunStepCount":0,"mSpeed":0.0,"mStartTime":0,"mStepCount":0,"mTimeUnit":600000,"mTotalActiveTime":0.0,"mWalkStepCount":0},{"mCalorie":0.0,"mDistance":0.0,"mNowHealthyStep":0,"mRunStepCount":0,"mSpeed":0.0,"mStartTime":0,"mStepCount":0,"mTimeUnit":600000,"mTotalActiveTime":0.0,"mWalkStepCount":0},{"mCalorie":0.0,"mDistance":0.0,"mNowHealthyStep":0,"mRunStepCount":0,"mSpeed":0.0,"mStartTime":0,"mStepCount":0,"mTimeUnit":600000,"mTotalActiveTime":0.0,"mWalkStepCount":0},{"mCalorie":0.0,"mDistance":0.0,"mNowHealthyStep":0,"mRunStepCount":0,"mSpeed":0.0,"mStartTime":0,"mStepCount":0,"mTimeUnit":600000,"mTotalActiveTime":0.0,"mWalkStepCount":0},{"mCalorie":0.0,"mDistance":0.0,"mNowHealthyStep":0,"mRunStepCount":0,"mSpeed":0.0,"mStartTime":0,"mStepCount":0,"mTimeUnit":600000,"mTotalActiveTime":0.0,"mWalkStepCount":0},{"mCalorie":0.0,"mDistance":0.0,"mNowHealthyStep":0,"mRunStepCount":0,"mSpeed":0.0,"mStartTime":0,"mStepCount":0,"mTimeUnit":600000,"mTotalActiveTime":0.0,"mWalkStepCount":0},{"mCalorie":0.0,"mDistance":0.0,"mNowHealthyStep":0,"mRunStepCount":0,"mSpeed":0.0,"mStartTime":0,"mStepCount":0,"mTimeUnit":600000,"mTotalActiveTime":0.0,"mWalkStepCount":0},{"mCalorie":0.0,"mDistance":0.0,"mNowHealthyStep":0,"mRunStepCount":0,"mSpeed":0.0,"mStartTime":0,"mStepCount":0,"mTimeUnit":600000,"mTotalActiveTime":0.0,"mWalkStepCount":0},{"mCalorie":0.0,"mDistance":0.0,"mNowHealthyStep":0,"mRunStepCount":0,"mSpeed":0.0,"mStartTime":0,"mStepCount":0,"mTimeUnit":600000,"mTotalActiveTime":0.0,"mWalkStepCount":0},{"mCalorie":0.0,"mDistance":0.0,"mNowHealthyStep":0,"mRunStepCount":0,"mSpeed":0.0,"mStartTime":0,"mStepCount":0,"mTimeUnit":600000,"mTotalActiveTime":0.0,"mWalkStepCount":0},{"mCalorie":0.0,"mDistance":0.0,"mNowHealthyStep":0,"mRunStepCount":0,"mSpeed":0.0,"mStartTime":0,"mStepCount":0,"mTimeUnit":600000,"mTotalActiveTime":0.0,"mWalkStepCount":0},{"mCalorie":0.0,"mDistance":0.0,"mNowHealthyStep":0,"mRunStepCount":0,"mSpeed":0.0,"mStartTime":0,"mStepCount":0,"mTimeUnit":600000,"mTotalActiveTime":0.0,"mWalkStepCount":0},{"mCalorie":0.0,"mDistance":0.0,"mNowHealthyStep":0,"mRunStepCount":0,"mSpeed":0.0,"mStartTime":0,"mStepCount":0,"mTimeUnit":600000,"mTotalActiveTime":0.0,"mWalkStepCount":0},{"mCalorie":0.0,"mDistance":0.0,"mNowHealthyStep":0,"mRunStepCount":0,"mSpeed":0.0,"mStartTime":0,"mStepCount":0,"mTimeUnit":600000,"mTotalActiveTime":0.0,"mWalkStepCount":0},{"mCalorie":0.0,"mDistance":0.0,"mNowHealthyStep":0,"mRunStepCount":0,"mSpeed":0.0,"mStartTime":0,"mStepCount":0,"mTimeUnit":600000,"mTotalActiveTime":0.0,"mWalkStepCount":0},{"mCalorie":0.0,"mDistance":0.0,"mNowHealthyStep":0,"mRunStepCount":0,"mSpeed":0.0,"mStartTime":0,"mStepCount":0,"mTimeUnit":600000,"mTotalActiveTime":0.0,"mWalkStepCount":0},{"mCalorie":0.0,"mDistance":0.0,"mNowHealthyStep":0,"mRunStepCount":0,"mSpeed":0.0,"mStartTime":0,"mStepCount":0,"mTimeUnit":600000,"mTotalActiveTime":0.0,"mWalkStepCount":0},{"mCalorie":0.0,"mDistance":0.0,"mNowHealthyStep":0,"mRunStepCount":0,"mSpeed":0.0,"mStartTime":0,"mStepCount":0,"mTimeUnit":600000,"mTotalActiveTime":0.0,"mWalkStepCount":0},{"mCalorie":0.0,"mDistance":0.0,"mNowHealthyStep":0,"mRunStepCount":0,"mSpeed":0.0,"mStartTime":0,"mStepCount":0,"mTimeUnit":600000,"mTotalActiveTime":0.0,"mWalkStepCount":0},{"mCalorie":0.0,"mDistance":0.0,"mNowHealthyStep":0,"mRunStepCount":0,"mSpeed":0.0,"mStartTime":0,"mStepCount":0,"mTimeUnit":600000,"mTotalActiveTime":0.0,"mWalkStepCount":0},{"mCalorie":19.44021451473236,"mDistance":453.1206302642822,"mNowHealthyStep":0,"mRunStepCount":0,"mSpeed":5.341216564178467,"mStartTime":0,"mStepCount":588,"mTimeUnit":600000,"mTotalActiveTime":305404.9930761779,"mWalkStepCount":588},{"mCalorie":27.139999866485596,"mDistance":582.3399991989136,"mNowHealthyStep":0,"mRunStepCount":0,"mSpeed":5.2045392990112305,"mStartTime":0,"mStepCount":757,"mTimeUnit":600000,"mTotalActiveTime":402806.82789158064,"mWalkStepCount":757},{"mCalorie":3.3105762600898743,"mDistance":68.58156681060791,"mNowHealthyStep":0,"mRunStepCount":0,"mSpeed":5.011126518249512,"mStartTime":0,"mStepCount":91,"mTimeUnit":600000,"mTotalActiveTime":49269.09018345467,"mWalkStepCount":91},{"mCalorie":0.0,"mDistance":0.0,"mNowHealthyStep":0,"mRunStepCount":0,"mSpeed":0.0,"mStartTime":0,"mStepCount":0,"mTimeUnit":600000,"mTotalActiveTime":0.0,"mWalkStepCount":0},{"mCalorie":0.0,"mDistance":0.0,"mNowHealthyStep":0,"mRunStepCount":0,"mSpeed":0.0,"mStartTime":0,"mStepCount":0,"mTimeUnit":600000,"mTotalActiveTime":0.0,"mWalkStepCount":0},{"mCalorie":0.0,"mDistance":0.0,"mNowHealthyStep":0,"mRunStepCount":0,"mSpeed":0.0,"mStartTime":0,"mStepCount":0,"mTimeUnit":600000,"mTotalActiveTime":0.0,"mWalkStepCount":0},{"mCalorie":0.0,"mDistance":0.0,"mNowHealthyStep":0,"mRunStepCount":0,"mSpeed":0.0,"mStartTime":0,"mStepCount":0,"mTimeUnit":600000,"mTotalActiveTime":0.0,"mWalkStepCount":0},{"mCalorie":0.0,"mDistance":0.0,"mNowHealthyStep":0,"mRunStepCount":0,"mSpeed":0.0,"mStartTime":0,"mStepCount":0,"mTimeUnit":600000,"mTotalActiveTime":0.0,"mWalkStepCount":0},{"mCalorie":3.510273367166519,"mDistance":74.49531269073486,"mNowHealthyStep":0,"mRunStepCount":0,"mSpeed":4.411345481872559,"mStartTime":0,"mStepCount":102,"mTimeUnit":600000,"mTotalActiveTime":60793.95216639716,"mWalkStepCount":102},{"mCalorie":0.0,"mDistance":0.0,"mNowHealthyStep":0,"mRunStepCount":0,"mSpeed":0.0,"mStartTime":0,"mStepCount":0,"mTimeUnit":600000,"mTotalActiveTime":0.0,"mWalkStepCount":0},{"mCalorie":3.3199999034404755,"mDistance":68.16000080108643,"mNowHealthyStep":0,"mRunStepCount":0,"mSpeed":4.61767578125,"mStartTime":0,"mStepCount":91,"mTimeUnit":600000,"mTotalActiveTime":53138.42040210324,"mWalkStepCount":91},{"mCalorie":4.120000034570694,"mDistance":87.7400016784668,"mNowHealthyStep":0,"mRunStepCount":0,"mSpeed":4.927886486053467,"mStartTime":0,"mStepCount":117,"mTimeUnit":600000,"mTotalActiveTime":64097.25856325966,"mWalkStepCount":117},{"mCalorie":2.4400000274181366,"mDistance":51.519999504089355,"mNowHealthyStep":0,"mRunStepCount":0,"mSpeed":4.428385257720947,"mStartTime":0,"mStepCount":70,"mTimeUnit":600000,"mTotalActiveTime":41882.53636007859,"mWalkStepCount":70},{"mCalorie":9.320000112056732,"mDistance":194.97999572753906,"mNowHealthyStep":0,"mRunStepCount":0,"mSpeed":4.579931735992432,"mStartTime":0,"mStepCount":263,"mTimeUnit":600000,"mTotalActiveTime":153261.675003678,"mWalkStepCount":263},{"mCalorie":3.259999990463257,"mDistance":69.68000030517578,"mNowHealthyStep":0,"mRunStepCount":0,"mSpeed":4.900000095367432,"mStartTime":0,"mStepCount":92,"mTimeUnit":600000,"mTotalActiveTime":51193.46861560065,"mWalkStepCount":92},{"mCalorie":11.74026358127594,"mDistance":243.93625450134277,"mNowHealthyStep":0,"mRunStepCount":0,"mSpeed":4.531764984130859,"mStartTime":0,"mStepCount":330,"mTimeUnit":600000,"mTotalActiveTime":193781.12039596183,"mWalkStepCount":330},{"mCalorie":10.060175776481628,"mDistance":219.39687633514404,"mNowHealthyStep":0,"mRunStepCount":0,"mSpeed":5.228233814239502,"mStartTime":0,"mStepCount":287,"mTimeUnit":600000,"mTotalActiveTime":151069.90123410232,"mWalkStepCount":287},{"mCalorie":1.159999966621399,"mDistance":24.309999465942383,"mNowHealthyStep":0,"mRunStepCount":0,"mSpeed":5.13204288482666,"mStartTime":0,"mStepCount":32,"mTimeUnit":600000,"mTotalActiveTime":17052.857948258363,"mWalkStepCount":32},{"mCalorie":0.0,"mDistance":0.0,"mNowHealthyStep":0,"mRunStepCount":0,"mSpeed":0.0,"mStartTime":0,"mStepCount":0,"mTimeUnit":600000,"mTotalActiveTime":0.0,"mWalkStepCount":0},{"mCalorie":0.0,"mDistance":0.0,"mNowHealthyStep":0,"mRunStepCount":0,"mSpeed":0.0,"mStartTime":0,"mStepCount":0,"mTimeUnit":600000,"mTotalActiveTime":0.0,"mWalkStepCount":0},{"mCalorie":0.0,"mDistance":0.0,"mNowHealthyStep":0,"mRunStepCount":0,"mSpeed":0.0,"mStartTime":0,"mStepCount":0,"mTimeUnit":600000,"mTotalActiveTime":0.0,"mWalkStepCount":0},{"mCalorie":0.0,"mDistance":0.0,"mNowHealthyStep":0,"mRunStepCount":0,"mSpeed":0.0,"mStartTime":0,"mStepCount":0,"mTimeUnit":600000,"mTotalActiveTime":0.0,"mWalkStepCount":0},{"mCalorie":1.0802050828933716,"mDistance":21.697500228881836,"mNowHealthyStep":0,"mRunStepCount":0,"mSpeed":4.162284851074219,"mStartTime":0,"mStepCount":30,"mTimeUnit":600000,"mTotalActiveTime":18766.375589074694,"mWalkStepCount":30},{"mCalorie":0.0,"mDistance":0.0,"mNowHealthyStep":0,"mRunStepCount":0,"mSpeed":0.0,"mStartTime":0,"mStepCount":0,"mTimeUnit":600000,"mTotalActiveTime":0.0,"mWalkStepCount":0},{"mCalorie":0.0,"mDistance":0.0,"mNowHealthyStep":0,"mRunStepCount":0,"mSpeed":0.0,"mStartTime":0,"mStepCount":0,"mTimeUnit":600000,"mTotalActiveTime":0.0,"mWalkStepCount":0},{"mCalorie":2.0000000298023224,"mDistance":45.820000648498535,"mNowHealthyStep":0,"mRunStepCount":0,"mSpeed":5.187670707702637,"mStartTime":0,"mStepCount":60,"mTimeUnit":600000,"mTotalActiveTime":31796.930469359286,"mWalkStepCount":60},{"mCalorie":0.0,"mDistance":0.0,"mNowHealthyStep":0,"mRunStepCount":0,"mSpeed":0.0,"mStartTime":0,"mStepCount":0,"mTimeUnit":600000,"mTotalActiveTime":0.0,"mWalkStepCount":0},{"mCalorie":13.130087852478027,"mDistance":281.0115671157837,"mNowHealthyStep":0,"mRunStepCount":0,"mSpeed":5.02093505859375,"mStartTime":0,"mStepCount":369,"mTimeUnit":600000,"mTotalActiveTime":201484.70760479936,"mWalkStepCount":369},{"mCalorie":11.490175545215607,"mDistance":241.48999309539795,"mNowHealthyStep":0,"mRunStepCount":0,"mSpeed":5.240248203277588,"mStartTime":0,"mStepCount":314,"mTimeUnit":600000,"mTotalActiveTime":165901.2946244131,"mWalkStepCount":314},{"mCalorie":0.0,"mDistance":0.0,"mNowHealthyStep":0,"mRunStepCount":0,"mSpeed":0.0,"mStartTime":0,"mStepCount":0,"mTimeUnit":600000,"mTotalActiveTime":0.0,"mWalkStepCount":0},{"mCalorie":0.0,"mDistance":0.0,"mNowHealthyStep":0,"mRunStepCount":0,"mSpeed":0.0,"mStartTime":0,"mStepCount":0,"mTimeUnit":600000,"mTotalActiveTime":0.0,"mWalkStepCount":0},{"mCalorie":0.0,"mDistance":0.0,"mNowHealthyStep":0,"mRunStepCount":0,"mSpeed":0.0,"mStartTime":0,"mStepCount":0,"mTimeUnit":600000,"mTotalActiveTime":0.0,"mWalkStepCount":0},{"mCalorie":12.26011711359024,"mDistance":278.9993782043457,"mNowHealthyStep":0,"mRunStepCount":0,"mSpeed":4.920611381530762,"mStartTime":0,"mStepCount":369,"mTimeUnit":600000,"mTotalActiveTime":204120.52817313955,"mWalkStepCount":369},{"mCalorie":12.690000176429749,"mDistance":264.0699996948242,"mNowHealthyStep":0,"mRunStepCount":0,"mSpeed":4.920297622680664,"mStartTime":0,"mStepCount":349,"mTimeUnit":600000,"mTotalActiveTime":193210.26339948102,"mWalkStepCount":349},{"mCalorie":0.0,"mDistance":0.0,"mNowHealthyStep":0,"mRunStepCount":0,"mSpeed":0.0,"mStartTime":0,"mStepCount":0,"mTimeUnit":600000,"mTotalActiveTime":0.0,"mWalkStepCount":0},{"mCalorie":0.0,"mDistance":0.0,"mNowHealthyStep":0,"mRunStepCount":0,"mSpeed":0.0,"mStartTime":0,"mStepCount":0,"mTimeUnit":600000,"mTotalActiveTime":0.0,"mWalkStepCount":0},{"mCalorie":0.0,"mDistance":0.0,"mNowHealthyStep":0,"mRunStepCount":0,"mSpeed":0.0,"mStartTime":0,"mStepCount":0,"mTimeUnit":600000,"mTotalActiveTime":0.0,"mWalkStepCount":0},{"mCalorie":2.650000035762787,"mDistance":54.60000133514404,"mNowHealthyStep":0,"mRunStepCount":0,"mSpeed":4.974526405334473,"mStartTime":0,"mStepCount":72,"mTimeUnit":600000,"mTotalActiveTime":39513.309693432115,"mWalkStepCount":72},{"mCalorie":1.7701562643051147,"mDistance":35.813438415527344,"mNowHealthyStep":0,"mRunStepCount":0,"mSpeed":5.56581974029541,"mStartTime":0,"mStepCount":46,"mTimeUnit":600000,"mTotalActiveTime":23164.310795493977,"mWalkStepCount":46},{"mCalorie":0.0,"mDistance":0.0,"mNowHealthyStep":0,"mRunStepCount":0,"mSpeed":0.0,"mStartTime":0,"mStepCount":0,"mTimeUnit":600000,"mTotalActiveTime":0.0,"mWalkStepCount":0},{"mCalorie":0.0,"mDistance":0.0,"mNowHealthyStep":0,"mRunStepCount":0,"mSpeed":0.0,"mStartTime":0,"mStepCount":0,"mTimeUnit":600000,"mTotalActiveTime":0.0,"mWalkStepCount":0},{"mCalorie":0.0,"mDistance":0.0,"mNowHealthyStep":0,"mRunStepCount":0,"mSpeed":0.0,"mStartTime":0,"mStepCount":0,"mTimeUnit":600000,"mTotalActiveTime":0.0,"mWalkStepCount":0},{"mCalorie":0.0,"mDistance":0.0,"mNowHealthyStep":0,"mRunStepCount":0,"mSpeed":0.0,"mStartTime":0,"mStepCount":0,"mTimeUnit":600000,"mTotalActiveTime":0.0,"mWalkStepCount":0},{"mCalorie":0.0,"mDistance":0.0,"mNowHealthyStep":0,"mRunStepCount":0,"mSpeed":0.0,"mStartTime":0,"mStepCount":0,"mTimeUnit":600000,"mTotalActiveTime":0.0,"mWalkStepCount":0},{"mCalorie":0.0,"mDistance":0.0,"mNowHealthyStep":0,"mRunStepCount":0,"mSpeed":0.0,"mStartTime":0,"mStepCount":0,"mTimeUnit":600000,"mTotalActiveTime":0.0,"mWalkStepCount":0},{"mCalorie":0.8299999833106995,"mDistance":19.479999542236328,"mNowHealthyStep":0,"mRunStepCount":0,"mSpeed":6.600000381469727,"mStartTime":0,"mStepCount":24,"mTimeUnit":600000,"mTotalActiveTime":10625.453681630586,"mWalkStepCount":24},{"mCalorie":17.1905275285244,"mDistance":356.8156261444092,"mNowHealthyStep":0,"mRunStepCount":0,"mSpeed":4.768916606903076,"mStartTime":0,"mStepCount":475,"mTimeUnit":600000,"mTotalActiveTime":269355.9905632758,"mWalkStepCount":475},{"mCalorie":3.110019564628601,"mDistance":65.35312461853027,"mNowHealthyStep":0,"mRunStepCount":0,"mSpeed":4.651822566986084,"mStartTime":0,"mStepCount":88,"mTimeUnit":600000,"mTotalActiveTime":50576.14408447174,"mWalkStepCount":88},{"mCalorie":0.0,"mDistance":0.0,"mNowHealthyStep":0,"mRunStepCount":0,"mSpeed":0.0,"mStartTime":0,"mStepCount":0,"mTimeUnit":600000,"mTotalActiveTime":0.0,"mWalkStepCount":0},{"mCalorie":0.0,"mDistance":0.0,"mNowHealthyStep":0,"mRunStepCount":0,"mSpeed":0.0,"mStartTime":0,"mStepCount":0,"mTimeUnit":600000,"mTotalActiveTime":0.0,"mWalkStepCount":0},{"mCalorie":2.4699999690055847,"mDistance":49.260000228881836,"mNowHealthyStep":0,"mRunStepCount":0,"mSpeed":4.8913774490356445,"mStartTime":0,"mStepCount":65,"mTimeUnit":600000,"mTotalActiveTime":36254.81925349249,"mWalkStepCount":65},{"mCalorie":2.8299999833106995,"mDistance":59.140000343322754,"mNowHealthyStep":0,"mRunStepCount":0,"mSpeed":4.872017860412598,"mStartTime":0,"mStepCount":79,"mTimeUnit":600000,"mTotalActiveTime":43699.3481331068,"mWalkStepCount":79},{"mCalorie":0.6100000143051147,"mDistance":11.989999771118164,"mNowHealthyStep":0,"mRunStepCount":0,"mSpeed":3.9000003337860107,"mStartTime":0,"mStepCount":17,"mTimeUnit":600000,"mTotalActiveTime":11067.69114917562,"mWalkStepCount":17},{"mCalorie":3.1400000005960464,"mDistance":62.750001311302185,"mNowHealthyStep":0,"mRunStepCount":0,"mSpeed":4.536409854888916,"mStartTime":0,"mStepCount":85,"mTimeUnit":600000,"mTotalActiveTime":49797.08859615789,"mWalkStepCount":85},{"mCalorie":4.78013688325882,"mDistance":103.9749984741211,"mNowHealthyStep":0,"mRunStepCount":0,"mSpeed":5.172164440155029,"mStartTime":0,"mStepCount":137,"mTimeUnit":600000,"mTotalActiveTime":72370.08944015848,"mWalkStepCount":137},{"mCalorie":15.060263872146606,"mDistance":338.0203170776367,"mNowHealthyStep":0,"mRunStepCount":0,"mSpeed":5.270471572875977,"mStartTime":0,"mStepCount":440,"mTimeUnit":600000,"mTotalActiveTime":230885.06862784192,"mWalkStepCount":440},{"mCalorie":8.900156259536743,"mDistance":210.84656524658203,"mNowHealthyStep":0,"mRunStepCount":0,"mSpeed":5.404009819030762,"mStartTime":0,"mStepCount":273,"mTimeUnit":600000,"mTotalActiveTime":140460.0768908835,"mWalkStepCount":273},{"mCalorie":0.0,"mDistance":0.0,"mNowHealthyStep":0,"mRunStepCount":0,"mSpeed":0.0,"mStartTime":0,"mStepCount":0,"mTimeUnit":600000,"mTotalActiveTime":0.0,"mWalkStepCount":0},{"mCalorie":0.38999998569488525,"mDistance":7.25,"mNowHealthyStep":0,"mRunStepCount":0,"mSpeed":3.9000003337860107,"mStartTime":0,"mStepCount":10,"mTimeUnit":600000,"mTotalActiveTime":6692.3071195388475,"mWalkStepCount":10},{"mCalorie":0.33000001311302185,"mDistance":7.409999847412109,"mNowHealthyStep":0,"mRunStepCount":0,"mSpeed":4.400000095367432,"mStartTime":0,"mStepCount":10,"mTimeUnit":600000,"mTotalActiveTime":6062.727016476566,"mWalkStepCount":10},{"mCalorie":5.550087928771973,"mDistance":123.0237512588501,"mNowHealthyStep":0,"mRunStepCount":0,"mSpeed":5.024356365203857,"mStartTime":0,"mStepCount":162,"mTimeUnit":600000,"mTotalActiveTime":88147.7105220454,"mWalkStepCount":162},{"mCalorie":3.949999898672104,"mDistance":82.07000064849854,"mNowHealthyStep":0,"mRunStepCount":0,"mSpeed":4.413218021392822,"mStartTime":0,"mStepCount":112,"mTimeUnit":600000,"mTotalActiveTime":66947.06449464697,"mWalkStepCount":112},{"mCalorie":1.3600000143051147,"mDistance":29.530000686645508,"mNowHealthyStep":0,"mRunStepCount":0,"mSpeed":5.022645473480225,"mStartTime":0,"mStepCount":39,"mTimeUnit":600000,"mTotalActiveTime":21165.738742237358,"mWalkStepCount":39},{"mCalorie":0.0,"mDistance":0.0,"mNowHealthyStep":0,"mRunStepCount":0,"mSpeed":0.0,"mStartTime":0,"mStepCount":0,"mTimeUnit":600000,"mTotalActiveTime":0.0,"mWalkStepCount":0},{"mCalorie":0.8199999928474426,"mDistance":18.260000228881836,"mNowHealthyStep":0,"mRunStepCount":0,"mSpeed":5.999999523162842,"mStartTime":0,"mStepCount":23,"mTimeUnit":600000,"mTotalActiveTime":10956.001008033832,"mWalkStepCount":23},{"mCalorie":1.149999976158142,"mDistance":22.05999994277954,"mNowHealthyStep":0,"mRunStepCount":0,"mSpeed":4.005627632141113,"mStartTime":0,"mStepCount":31,"mTimeUnit":600000,"mTotalActiveTime":19826.10535373318,"mWalkStepCount":31},{"mCalorie":0.0,"mDistance":0.0,"mNowHealthyStep":0,"mRunStepCount":0,"mSpeed":0.0,"mStartTime":0,"mStepCount":0,"mTimeUnit":600000,"mTotalActiveTime":0.0,"mWalkStepCount":0},{"mCalorie":0.0,"mDistance":0.0,"mNowHealthyStep":0,"mRunStepCount":0,"mSpeed":0.0,"mStartTime":0,"mStepCount":0,"mTimeUnit":600000,"mTotalActiveTime":0.0,"mWalkStepCount":0},{"mCalorie":0.0,"mDistance":0.0,"mNowHealthyStep":0,"mRunStepCount":0,"mSpeed":0.0,"mStartTime":0,"mStepCount":0,"mTimeUnit":600000,"mTotalActiveTime":0.0,"mWalkStepCount":0},{"mCalorie":0.0,"mDistance":0.0,"mNowHealthyStep":0,"mRunStepCount":0,"mSpeed":0.0,"mStartTime":0,"mStepCount":0,"mTimeUnit":600000,"mTotalActiveTime":0.0,"mWalkStepCount":0},{"mCalorie":0.0,"mDistance":0.0,"mNowHealthyStep":0,"mRunStepCount":0,"mSpeed":0.0,"mStartTime":0,"mStepCount":0,"mTimeUnit":600000,"mTotalActiveTime":0.0,"mWalkStepCount":0},{"mCalorie":0.0,"mDistance":0.0,"mNowHealthyStep":0,"mRunStepCount":0,"mSpeed":0.0,"mStartTime":0,"mStepCount":0,"mTimeUnit":600000,"mTotalActiveTime":0.0,"mWalkStepCount":0},{"mCalorie":0.0,"mDistance":0.0,"mNowHealthyStep":0,"mRunStepCount":0,"mSpeed":0.0,"mStartTime":0,"mStepCount":0,"mTimeUnit":600000,"mTotalActiveTime":0.0,"mWalkStepCount":0},{"mCalorie":0.0,"mDistance":0.0,"mNowHealthyStep":0,"mRunStepCount":0,"mSpeed":0.0,"mStartTime":0,"mStepCount":0,"mTimeUnit":600000,"mTotalActiveTime":0.0,"mWalkStepCount":0},{"mCalorie":0.0,"mDistance":0.0,"mNowHealthyStep":0,"mRunStepCount":0,"mSpeed":0.0,"mStartTime":0,"mStepCount":0,"mTimeUnit":600000,"mTotalActiveTime":0.0,"mWalkStepCount":0},{"mCalorie":0.38999998569488525,"mDistance":8.170000076293945,"mNowHealthyStep":0,"mRunStepCount":0,"mSpeed":4.600000381469727,"mStartTime":0,"mStepCount":11,"mTimeUnit":600000,"mTotalActiveTime":6393.912572950896,"mWalkStepCount":11},{"mCalorie":0.4399999976158142,"mDistance":8.760000228881836,"mNowHealthyStep":0,"mRunStepCount":0,"mSpeed":4.5,"mStartTime":0,"mStepCount":12,"mTimeUnit":600000,"mTotalActiveTime":7008.000183105469,"mWalkStepCount":12},{"mCalorie":0.3499999940395355,"mDistance":8.069999694824219,"mNowHealthyStep":0,"mRunStepCount":0,"mSpeed":6.399999618530273,"mStartTime":0,"mStepCount":10,"mTimeUnit":600000,"mTotalActiveTime":4539.375098906463,"mWalkStepCount":10},{"mCalorie":0.0,"mDistance":0.0,"mNowHealthyStep":0,"mRunStepCount":0,"mSpeed":0.0,"mStartTime":0,"mStepCount":0,"mTimeUnit":600000,"mTotalActiveTime":0.0,"mWalkStepCount":0},{"mCalorie":0.0,"mDistance":0.0,"mNowHealthyStep":0,"mRunStepCount":0,"mSpeed":0.0,"mStartTime":0,"mStepCount":0,"mTimeUnit":600000,"mTotalActiveTime":0.0,"mWalkStepCount":0},{"mCalorie":0.0,"mDistance":0.0,"mNowHealthyStep":0,"mRunStepCount":0,"mSpeed":0.0,"mStartTime":0,"mStepCount":0,"mTimeUnit":600000,"mTotalActiveTime":0.0,"mWalkStepCount":0},{"mCalorie":0.0,"mDistance":0.0,"mNowHealthyStep":0,"mRunStepCount":0,"mSpeed":0.0,"mStartTime":0,"mStepCount":0,"mTimeUnit":600000,"mTotalActiveTime":0.0,"mWalkStepCount":0},{"mCalorie":0.0,"mDistance":0.0,"mNowHealthyStep":0,"mRunStepCount":0,"mSpeed":0.0,"mStartTime":0,"mStepCount":0,"mTimeUnit":600000,"mTotalActiveTime":0.0,"mWalkStepCount":0},{"mCalorie":0.0,"mDistance":0.0,"mNowHealthyStep":0,"mRunStepCount":0,"mSpeed":0.0,"mStartTime":0,"mStepCount":0,"mTimeUnit":600000,"mTotalActiveTime":0.0,"mWalkStepCount":0},{"mCalorie":0.0,"mDistance":0.0,"mNowHealthyStep":0,"mRunStepCount":0,"mSpeed":0.0,"mStartTime":0,"mStepCount":0,"mTimeUnit":600000,"mTotalActiveTime":0.0,"mWalkStepCount":0}]