[{"score":13,"score_max":19,"score_min":3,"flag":1,"level":0,"start_time":1616457600000,"end_time":1616457659999},{"score":13,"score_max":16,"score_min":7,"flag":1,"level":0,"start_time":1616457660000,"end_time":1616457719999},{"score":98,"score_max":99,"score_min":98,"flag":1,"level":1,"start_time":1616457780000,"end_time":1616457839999},{"score":99,"score_max":99,"score_min":99,"flag":1,"level":1,"start_time":1616457840000,"end_time":1616457899999},{"score":8,"score_max":16,"score_min":0,"flag":1,"level":0,"start_time":1616459640000,"end_time":1616459699999},{"score":16,"score_max":24,"score_min":16,"flag":1,"level":0,"start_time":1616459700000,"end_time":1616459759999},{"score":15,"score_max":17,"score_min":11,"flag":1,"level":0,"start_time":1616459880000,"end_time":1616459939999},{"score":15,"score_max":19,"score_min":6,"flag":1,"level":0,"start_time":1616459940000,"end_time":1616459999999},{"score":14,"score_max":16,"score_min":13,"flag":1,"level":0,"start_time":1616460000000,"end_time":1616460059999},{"score":100,"score_max":100,"score_min":100,"flag":1,"level":1,"start_time":1616460180000,"end_time":1616460239999},{"score":100,"score_max":100,"score_min":100,"flag":1,"level":1,"start_time":1616460240000,"end_time":1616460299999},{"score":28,"score_max":33,"score_min":26,"flag":1,"level":0,"start_time":1616460420000,"end_time":1616460479999},{"score":86,"score_max":100,"score_min":36,"flag":1,"level":1,"start_time":1616460480000,"end_time":1616460539999},{"score":99,"score_max":99,"score_min":99,"flag":1,"level":1,"start_time":1616460840000,"end_time":1616460899999},{"score":98,"score_max":99,"score_min":98,"flag":1,"level":1,"start_time":1616460900000,"end_time":1616460959999},{"score":98,"score_max":98,"score_min":98,"flag":1,"level":1,"start_time":1616460960000,"end_time":1616461019999},{"score":100,"score_max":100,"score_min":100,"flag":1,"level":1,"start_time":1616461080000,"end_time":1616461139999},{"score":99,"score_max":100,"score_min":99,"flag":1,"level":1,"start_time":1616461140000,"end_time":1616461199999}]