[{"calorie":0.0,"count":0,"distance":0.0,"speed":0.0},{"calorie":0.0,"count":0,"distance":0.0,"speed":0.0},{"calorie":0.0,"count":0,"distance":0.0,"speed":0.0},{"calorie":0.0,"count":0,"distance":0.0,"speed":0.0},{"calorie":0.0,"count":0,"distance":0.0,"speed":0.0},{"calorie":0.0,"count":0,"distance":0.0,"speed":0.0},{"calorie":0.0,"count":0,"distance":0.0,"speed":0.0},{"calorie":0.0,"count":0,"distance":0.0,"speed":0.0},{"calorie":0.0,"count":0,"distance":0.0,"speed":0.0},{"calorie":0.0,"count":0,"distance":0.0,"speed":0.0},{"calorie":0.0,"count":0,"distance":0.0,"speed":0.0},{"calorie":0.0,"count":0,"distance":0.0,"speed":0.0},{"calorie":0.0,"count":0,"distance":0.0,"speed":0.0},{"calorie":0.0,"count":0,"distance":0.0,"speed":0.0},{"calorie":0.0,"count":0,"distance":0.0,"speed":0.0},{"calorie":0.0,"count":0,"distance":0.0,"speed":0.0},{"calorie":0.0,"count":0,"distance":0.0,"speed":0.0},{"calorie":0.0,"count":0,"distance":0.0,"speed":0.0},{"calorie":0.0,"count":0,"distance":0.0,"speed":0.0},{"calorie":0.0,"count":0,"distance":0.0,"speed":0.0},{"calorie":0.0,"count":0,"distance":0.0,"speed":0.0},{"calorie":0.0,"count":0,"distance":0.0,"speed":0.0},{"calorie":0.0,"count":0,"distance":0.0,"speed":0.0},{"calorie":0.0,"count":0,"distance":0.0,"speed":0.0},{"calorie":0.0,"count":0,"distance":0.0,"speed":0.0},{"calorie":0.0,"count":0,"distance":0.0,"speed":0.0},{"calorie":0.0,"count":0,"distance":0.0,"speed":0.0},{"calorie":0.0,"count":0,"distance":0.0,"speed":0.0},{"calorie":0.0,"count":0,"distance":0.0,"speed":0.0},{"calorie":0.0,"count":0,"distance":0.0,"speed":0.0},{"calorie":0.0,"count":0,"distance":0.0,"speed":0.0},{"calorie":0.0,"count":0,"distance":0.0,"speed":0.0},{"calorie":0.0,"count":0,"distance":0.0,"speed":0.0},{"calorie":0.0,"count":0,"distance":0.0,"speed":0.0},{"calorie":0.0,"count":0,"distance":0.0,"speed":0.0},{"calorie":0.0,"count":0,"distance":0.0,"speed":0.0},{"calorie":0.0,"count":0,"distance":0.0,"speed":0.0},{"calorie":0.0,"count":0,"distance":0.0,"speed":0.0},{"calorie":0.0,"count":0,"distance":0.0,"speed":0.0},{"calorie":0.0,"count":0,"distance":0.0,"speed":0.0},{"calorie":0.0,"count":0,"distance":0.0,"speed":0.0},{"calorie":0.0,"count":0,"distance":0.0,"speed":0.0},{"calorie":0.0,"count":0,"distance":0.0,"speed":0.0},{"calorie":0.0,"count":0,"distance":0.0,"speed":0.0},{"calorie":0.0,"count":0,"distance":0.0,"speed":0.0},{"calorie":0.0,"count":0,"distance":0.0,"speed":0.0},{"calorie":0.0,"count":0,"distance":0.0,"speed":0.0},{"calorie":0.0,"count":0,"distance":0.0,"speed":0.0},{"calorie":0.0,"count":0,"distance":0.0,"speed":0.0},{"calorie":0.0,"count":0,"distance":0.0,"speed":0.0},{"calorie":0.0,"count":0,"distance":0.0,"speed":0.0},{"calorie":1.6499998569488525,"count":33,"distance":24.58000135421753,"speed":4.379222393035889},{"calorie":0.8600000143051147,"count":16,"distance":11.670000076293945,"speed":4.023617267608643},{"calorie":0.0,"count":0,"distance":0.0,"speed":0.0},{"calorie":0.0,"count":0,"distance":0.0,"speed":0.0},{"calorie":0.0,"count":0,"distance":0.0,"speed":0.0},{"calorie":0.0,"count":0,"distance":0.0,"speed":0.0},{"calorie":0.0,"count":0,"distance":0.0,"speed":0.0},{"calorie":0.0,"count":0,"distance":0.0,"speed":0.0},{"calorie":0.0,"count":0,"distance":0.0,"speed":0.0},{"calorie":0.0,"count":0,"distance":0.0,"speed":0.0},{"calorie":0.0,"count":0,"distance":0.0,"speed":0.0},{"calorie":0.0,"count":0,"distance":0.0,"speed":0.0},{"calorie":0.0,"count":0,"distance":0.0,"speed":0.0},{"calorie":1.2999999523162842,"count":26,"distance":19.200000762939453,"speed":4.1942219734191895},{"calorie":1.2999999523162842,"count":25,"distance":18.780000686645508,"speed":4.900000095367432},{"calorie":0.0,"count":0,"distance":0.0,"speed":0.0},{"calorie":0.0,"count":0,"distance":0.0,"speed":0.0},{"calorie":0.0,"count":0,"distance":0.0,"speed":0.0},{"calorie":0.0,"count":0,"distance":0.0,"speed":0.0},{"calorie":8.040000233650208,"count":157,"distance":121.90000099182129,"speed":5.390319347381592},{"calorie":5.8900000190734865,"count":116,"distance":88.8099983215332,"speed":4.901808261871338},{"calorie":0.48,"count":10,"distance":7.97,"speed":5.5},{"calorie":0.57,"count":10,"distance":6.87,"speed":3.200000047683716},{"calorie":27.869997806549065,"count":535,"distance":411.5900238037113,"speed":5.1212873458862305},{"calorie":5.040000000000032,"count":93,"distance":67.51000000000109,"speed":4.305703639984131},{"calorie":6.740000000000063,"count":115,"distance":89.19899999999927,"speed":5.5196852684021},{"calorie":15.809999557733535,"count":312,"distance":241.63099996185085,"speed":5.200970649719238},{"calorie":2.08,"count":36,"distance":27.019999999999996,"speed":4.4693169593811035},{"calorie":20.46000018119812,"count":391,"distance":299.19999691009525,"speed":5.133479595184326},{"calorie":11.76999847888951,"count":236,"distance":181.64904123687694,"speed":5.061259746551514},{"calorie":0.0,"count":0,"distance":0.0,"speed":0.0},{"calorie":0.0,"count":0,"distance":0.0,"speed":0.0},{"calorie":31.050002150535583,"count":618,"distance":470.1999462890625,"speed":4.852472305297852},{"calorie":31.009999999999934,"count":554,"distance":398.53999999999957,"speed":4.905259609222412},{"calorie":0.0,"count":0,"distance":0.0,"speed":0.0},{"calorie":0.0,"count":0,"distance":0.0,"speed":0.0},{"calorie":0.0,"count":0,"distance":0.0,"speed":0.0},{"calorie":0.0,"count":0,"distance":0.0,"speed":0.0},{"calorie":0.0,"count":0,"distance":0.0,"speed":0.0},{"calorie":12.290000002384186,"count":241,"distance":189.35000015258788,"speed":5.593797206878662},{"calorie":13.82000021457672,"count":270,"distance":201.13000217437747,"speed":4.4952545166015625},{"calorie":8.189999809265082,"count":165,"distance":127.25100915527254,"speed":5.103466033935547},{"calorie":0.0,"count":0,"distance":0.0,"speed":0.0},{"calorie":1.039999999999968,"count":21,"distance":17.529000000000963,"speed":7.025034427642822},{"calorie":32.399999904632566,"count":643,"distance":483.73999786376953,"speed":4.638029098510742},{"calorie":0.68,"count":14,"distance":11.62,"speed":6.800000190734863},{"calorie":0.0,"count":0,"distance":0.0,"speed":0.0},{"calorie":0.36000001430511475,"count":7,"distance":5.539999961853027,"speed":5.614044666290283},{"calorie":18.03,"count":360,"distance":274.1700012207031,"speed":4.823482990264893},{"calorie":0.0,"count":0,"distance":0.0,"speed":0.0},{"calorie":0.0,"count":0,"distance":0.0,"speed":0.0},{"calorie":23.89999984741211,"count":474,"distance":358.40999511718746,"speed":4.673439979553223},{"calorie":2.589999986886978,"count":48,"distance":37.88999992370606,"speed":5.518255233764648},{"calorie":0.0,"count":0,"distance":0.0,"speed":0.0},{"calorie":0.0,"count":0,"distance":0.0,"speed":0.0},{"calorie":0.0,"count":0,"distance":0.0,"speed":0.0},{"calorie":0.0,"count":0,"distance":0.0,"speed":0.0},{"calorie":0.0,"count":0,"distance":0.0,"speed":0.0},{"calorie":0.0,"count":0,"distance":0.0,"speed":0.0},{"calorie":0.0,"count":0,"distance":0.0,"speed":0.0},{"calorie":0.0,"count":0,"distance":0.0,"speed":0.0},{"calorie":0.0,"count":0,"distance":0.0,"speed":0.0},{"calorie":0.0,"count":0,"distance":0.0,"speed":0.0},{"calorie":0.0,"count":0,"distance":0.0,"speed":0.0},{"calorie":0.0,"count":0,"distance":0.0,"speed":0.0},{"calorie":0.0,"count":0,"distance":0.0,"speed":0.0},{"calorie":0.0,"count":0,"distance":0.0,"speed":0.0},{"calorie":0.0,"count":0,"distance":0.0,"speed":0.0},{"calorie":0.0,"count":0,"distance":0.0,"speed":0.0},{"calorie":0.0,"count":0,"distance":0.0,"speed":0.0},{"calorie":0.0,"count":0,"distance":0.0,"speed":0.0},{"calorie":1.89000004529953,"count":36,"distance":27.24000072479248,"speed":4.503939151763916},{"calorie":0.6700000166893005,"count":13,"distance":9.789999961853027,"speed":4.299999713897705},{"calorie":0.0,"count":0,"distance":0.0,"speed":0.0},{"calorie":0.0,"count":0,"distance":0.0,"speed":0.0},{"calorie":0.0,"count":0,"distance":0.0,"speed":0.0},{"calorie":2.36,"count":46,"distance":35.24,"speed":5.099999904632568},{"calorie":27.330000171661357,"count":534,"distance":416.0990030517572,"speed":5.287707328796387},{"calorie":7.070000000000001,"count":136,"distance":103.41,"speed":4.7644758224487305},{"calorie":6.370000026226111,"count":126,"distance":96.0890000762944,"speed":5.190796852111816},{"calorie":0.0,"count":0,"distance":0.0,"speed":0.0},{"calorie":5.450000057220527,"count":106,"distance":80.61999805450526,"speed":4.8388824462890625},{"calorie":12.819999999999997,"count":243,"distance":182.3999999999994,"speed":4.497581958770752},{"calorie":0.0,"count":0,"distance":0.0,"speed":0.0},{"calorie":0.0,"count":0,"distance":0.0,"speed":0.0},{"calorie":0.0,"count":0,"distance":0.0,"speed":0.0},{"calorie":0.0,"count":0,"distance":0.0,"speed":0.0},{"calorie":0.0,"count":0,"distance":0.0,"speed":0.0},{"calorie":0.0,"count":0,"distance":0.0,"speed":0.0},{"calorie":0.0,"count":0,"distance":0.0,"speed":0.0},{"calorie":0.6999999999999318,"count":16,"distance":12.510000000000218,"speed":5.310739994049072},{"calorie":0.0,"count":0,"distance":0.0,"speed":0.0},{"calorie":0.0,"count":0,"distance":0.0,"speed":0.0}]