[{"score":13,"score_max":16,"score_min":8,"flag":1,"level":0,"start_time":1607516520000,"end_time":1607516579999},{"score":16,"score_max":19,"score_min":16,"flag":1,"level":0,"start_time":1607516580000,"end_time":1607516639999},{"score":6,"score_max":9,"score_min":3,"flag":1,"level":0,"start_time":1607518260000,"end_time":1607518319999},{"score":16,"score_max":37,"score_min":9,"flag":1,"level":0,"start_time":1607518320000,"end_time":1607518379999},{"score":43,"score_max":46,"score_min":39,"flag":1,"level":0,"start_time":1607518380000,"end_time":1607518439999},{"score":96,"score_max":97,"score_min":96,"flag":1,"level":1,"start_time":1607518500000,"end_time":1607518559999},{"score":12,"score_max":15,"score_min":10,"flag":1,"level":0,"start_time":1607518680000,"end_time":1607518739999},{"score":16,"score_max":17,"score_min":15,"flag":1,"level":0,"start_time":1607518740000,"end_time":1607518799999}]